{
    "_": "Message",
    "id": 978,
    "from_user": {
        "_": "User",
        "id": 1234567890,
        "is_self": false,
        "is_contact": false,
        "is_mutual_contact": false,
        "is_deleted": false,
        "is_bot": false,
        "is_verified": false,
        "is_restricted": false,
        "is_scam": false,
        "is_fake": false,
        "is_support": false,
        "is_premium": false,
        "first_name": "mærd",
        "status": "UserStatus.RECENTLY",
        "username": "maerxd",
        "language_code": "ru",
        "dc_id": 2,
        "photo": {
            "_": "ChatPhoto",
            "small_file_id": "AQADAgADntAxG2lTIEoAEAIAA1ryEkoABGP5-XIaTm7zAAQeBA",
            "small_photo_unique_id": "AgADntAxG2lTIEo",
            "big_file_id": "AQADAgADntAxG2lTIEoAEAMAA1ryEkoABGP5-XIaTm7zAAQeBA",
            "big_photo_unique_id": "AgADntAxG2lTIEo"
        }
    },
    "date": "2024-04-11 18:21:40",
    "chat": {
        "_": "Chat",
        "id": 1242755674,
        "type": "ChatType.PRIVATE",
        "is_verified": false,
        "is_restricted": false,
        "is_scam": false,
        "is_fake": false,
        "is_support": false,
        "username": "maerxd",
        "first_name": "mærd",
        "photo": {
            "_": "ChatPhoto",
            "small_file_id": "AQADAgADntAxG2lTIEoAEAIAA1ryEkoABGP5-XIaTm7zAAQeBA",
            "small_photo_unique_id": "AgADntAxG2lTIEo",
            "big_file_id": "AQADAgADntAxG2lTIEoAEAMAA1ryEkoABGP5-XIaTm7zAAQeBA",
            "big_photo_unique_id": "AgADntAxG2lTIEo"
        },
        "dc_id": 2
    },
    "mentioned": false,
    "scheduled": false,
    "from_scheduled": false,
    "has_protected_content": false,
    "text": "/start",
    "entities": [
        {
            "_": "MessageEntity",
            "type": "MessageEntityType.BOT_COMMAND",
            "offset": 0,
            "length": 6
        }
    ],
    "outgoing": false,
    "command": [
        "start"
    ]
}